guolei_py3_tiehu/__init__.py
guolei_py3_tiehu/library/__init__.py
guolei_py3_tiehu/library/parking.py
guolei_py3_tiehu-2.1.0.dist-info/LICENSE
guolei_py3_tiehu-2.1.0.dist-info/METADATA
guolei_py3_tiehu-2.1.0.dist-info/WHEEL
guolei_py3_tiehu-2.1.0.dist-info/top_level.txt
guolei_py3_tiehu-2.1.0.dist-info/RECORD
