Metadata-Version: 2.1
Name: guolei-py3-tiehu
Version: 2.1.0
Summary: 铁虎 API
Home-page: https://github.com/guolei19850528/guolei_py3_tiehu
Author: guolei
Author-email: 174000902@qq.com
License: MIT
Requires-Python: >=3.0
License-File: LICENSE
Requires-Dist: guolei-py3-requests
Requires-Dist: requests
Requires-Dist: addict
Requires-Dist: retrying
Requires-Dist: jsonschema
